MANIFEST.in
README.md
setup.py
infra_buddy/__init__.py
infra_buddy/commandline.py
infra_buddy.egg-info/PKG-INFO
infra_buddy.egg-info/SOURCES.txt
infra_buddy.egg-info/dependency_links.txt
infra_buddy.egg-info/namespace_packages.txt
infra_buddy.egg-info/requires.txt
infra_buddy.egg-info/top_level.txt
infra_buddy.egg-info/zip-safe
infra_buddy/aws/__init__.py
infra_buddy/aws/cloudformation.py
infra_buddy/aws/ecs.py
infra_buddy/aws/s3.py
infra_buddy/commands/__init__.py
infra_buddy/commands/bootstrap/__init__.py
infra_buddy/commands/bootstrap/command.py
infra_buddy/commands/deploy_cloudformation/__init__.py
infra_buddy/commands/deploy_cloudformation/command.py
infra_buddy/commands/deploy_service/__init__.py
infra_buddy/commands/deploy_service/command.py
infra_buddy/commands/generate_artifact_manifest/__init__.py
infra_buddy/commands/generate_artifact_manifest/command.py
infra_buddy/commands/generate_service_definition/__init__.py
infra_buddy/commands/generate_service_definition/command.py
infra_buddy/commands/introspect/__init__.py
infra_buddy/commands/introspect/command.py
infra_buddy/commands/validate_template/__init__.py
infra_buddy/commands/validate_template/command.py
infra_buddy/context/__init__.py
infra_buddy/context/artifact_definition.py
infra_buddy/context/deploy_ctx.py
infra_buddy/context/monitor_definition.py
infra_buddy/context/service_definition.py
infra_buddy/deploy/__init__.py
infra_buddy/deploy/cloudformation_deploy.py
infra_buddy/deploy/datadog_monitor_deploy.py
infra_buddy/deploy/deploy.py
infra_buddy/deploy/ecs_deploy.py
infra_buddy/deploy/s3_deploy.py
infra_buddy/notifier/__init__.py
infra_buddy/notifier/datadog_notifier.py
infra_buddy/template/__init__.py
infra_buddy/template/builtin-templates.json
infra_buddy/template/template.py
infra_buddy/template/template_manager.py
infra_buddy/utility/__init__.py
infra_buddy/utility/exception.py
infra_buddy/utility/helper_functions.py
infra_buddy/utility/print_utility.py
infra_buddy/utility/waitfor.py
scripts/infra-buddy