Metadata-Version: 1.1
Name: infra-buddy
Version: 0.1.139
Summary: CLI for deploying micro-services
Home-page: https://github.com/AlienVault-Engineering/infra-buddy
Author: UNKNOWN
Author-email: UNKNOWN
License: Apache 2.0
Platform: UNKNOWN
Classifier: Development Status :: 3 - Alpha
Classifier: Programming Language :: Python
